CHANGES.rst
DESCRIPTION.rst
MANIFEST.in
README.md
setup.cfg
setup.py
python/python_weka_wrapper.egg-info/PKG-INFO
python/python_weka_wrapper.egg-info/SOURCES.txt
python/python_weka_wrapper.egg-info/dependency_links.txt
python/python_weka_wrapper.egg-info/entry_points.txt
python/python_weka_wrapper.egg-info/requires.txt
python/python_weka_wrapper.egg-info/top_level.txt
python/weka/__init__.py
python/weka/associations.py
python/weka/attribute_selection.py
python/weka/classifiers.py
python/weka/clusterers.py
python/weka/datagenerators.py
python/weka/experiments.py
python/weka/filters.py
python/weka/core/__init__.py
python/weka/core/capabilities.py
python/weka/core/classes.py
python/weka/core/converters.py
python/weka/core/database.py
python/weka/core/dataset.py
python/weka/core/jvm.py
python/weka/core/packages.py
python/weka/core/serialization.py
python/weka/core/stemmers.py
python/weka/core/stopwords.py
python/weka/core/tokenizers.py
python/weka/core/types.py
python/weka/core/version.py
python/weka/flow/__init__.py
python/weka/flow/base.py
python/weka/flow/container.py
python/weka/flow/control.py
python/weka/flow/conversion.py
python/weka/flow/sink.py
python/weka/flow/source.py
python/weka/flow/transformer.py
python/weka/lib/python-weka-wrapper-src.jar
python/weka/lib/python-weka-wrapper.jar
python/weka/lib/weka.jar
python/weka/plot/__init__.py
python/weka/plot/classifiers.py
python/weka/plot/clusterers.py
python/weka/plot/dataset.py
python/weka/plot/experiments.py
python/weka/plot/graph.py