Metadata-Version: 2.1
Name: python-weka-wrapper
Version: 0.3.16
Summary: Python wrapper for the Weka Machine Learning Workbench
Home-page: https://github.com/fracpete/python-weka-wrapper
Author: Peter "fracpete" Reutemann
Author-email: pythonwekawrapper@gmail.com
License: GNU General Public License version 3.0 (GPLv3)
Platform: UNKNOWN
Classifier: Development Status :: 4 - Beta
Classifier: License :: OSI Approved :: GNU General Public License (GPL)
Classifier: Topic :: Scientific/Engineering :: Artificial Intelligence
Classifier: Programming Language :: Python :: 2.7
Provides-Extra: graphs
Provides-Extra: plots
